CHANGES.txt
LICENSE.txt
MANIFEST.in
README.rst
requirements.txt
setup.py
retry_decorator/__init__.py
retry_decorator/retry_decorator.py
retry_decorator.egg-info/PKG-INFO
retry_decorator.egg-info/SOURCES.txt
retry_decorator.egg-info/dependency_links.txt
retry_decorator.egg-info/top_level.txt