Metadata-Version: 1.1
Name: retry_decorator
Version: 1.1.0
Summary: Retry Decorator
Home-page: https://github.com/pnpnpn/retry-decorator
Author: Patrick Ng
Author-email: pn.appdev@gmail.com
License: MIT
Platform: UNKNOWN
Classifier: Programming Language :: Python :: 2
Classifier: Programming Language :: Python :: 3
